audible_cli/__init__.py
audible_cli/__main__.py
audible_cli/_logging.py
audible_cli/_version.py
audible_cli/cli.py
audible_cli/config.py
audible_cli/constants.py
audible_cli/decorators.py
audible_cli/downloader.py
audible_cli/exceptions.py
audible_cli/models.py
audible_cli/plugins.py
audible_cli/utils.py
audible_cli/cmds/__init__.py
audible_cli/cmds/cmd_activation_bytes.py
audible_cli/cmds/cmd_api.py
audible_cli/cmds/cmd_download.py
audible_cli/cmds/cmd_library.py
audible_cli/cmds/cmd_manage.py
audible_cli/cmds/cmd_quickstart.py
audible_cli/cmds/cmd_wishlist.py
audible_cli-0.3.3.dist-info/METADATA
audible_cli-0.3.3.dist-info/WHEEL
audible_cli-0.3.3.dist-info/entry_points.txt
audible_cli-0.3.3.dist-info/licenses/LICENSE
audible_cli-0.3.3.dist-info/RECORD
