Metadata-Version: 2.4
Name: audible-cli
Version: 0.3.3
Summary: Command line interface (cli) for the audible package.
Project-URL: Changelog, https://github.com/mkb79/audible-cli/releases
Author-email: mkb79 <mkb79@hackitall.de>
License-Expression: AGPL-3.0-only
License-File: LICENSE
Keywords: API,Audible,async,cli
Classifier: Development Status :: 4 - Beta
Classifier: Intended Audience :: Developers
Classifier: License :: OSI Approved :: GNU Affero General Public License v3
Classifier: Programming Language :: Python :: 3.6
Classifier: Programming Language :: Python :: 3.7
Classifier: Programming Language :: Python :: 3.8
Classifier: Programming Language :: Python :: 3.9
Classifier: Programming Language :: Python :: 3.10
Classifier: Programming Language :: Python :: 3.11
Classifier: Programming Language :: Python :: 3.12
Classifier: Programming Language :: Python :: 3.13
Requires-Python: <3.14,>=3.10
Requires-Dist: aiofiles
Requires-Dist: audible>=0.8.2
Requires-Dist: click>=8
Requires-Dist: colorama; platform_system == 'Windows'
Requires-Dist: httpx<0.28.0,>=0.23.3
Requires-Dist: packaging
Requires-Dist: pillow
Requires-Dist: questionary
Requires-Dist: tabulate
Requires-Dist: toml
Requires-Dist: tqdm
